pockey/pockey.py
pockey-0.1.dist-info/METADATA
pockey-0.1.dist-info/WHEEL
pockey-0.1.dist-info/top_level.txt
pockey-0.1.dist-info/RECORD
