Metadata-Version: 2.1
Name: pockey
Version: 0.1
Summary: This is an OTP generator
Home-page: UNKNOWN
Author: Rishikesh Patvardhan
Author-email: riship14999@gmail.com
License: UNKNOWN
Platform: UNKNOWN
